cellsim/__init__.py
cellsim/pac.py
cellsim-1.0.1.dist-info/METADATA
cellsim-1.0.1.dist-info/WHEEL
cellsim-1.0.1.dist-info/licenses/LICENSE
cellsim-1.0.1.dist-info/RECORD
